gauge_pybuild_plugin/__init__.py
gauge_pybuild_plugin/cli.py
gauge_pybuild_plugin/core.py
gauge_pybuild_plugin/poetry_plugin.py
gauge_pybuild_plugin/setuptools_command.py
gauge_pybuild_plugin-0.1.0.dist-info/METADATA
gauge_pybuild_plugin-0.1.0.dist-info/WHEEL
gauge_pybuild_plugin-0.1.0.dist-info/entry_points.txt
gauge_pybuild_plugin-0.1.0.dist-info/licenses/LICENSE
gauge_pybuild_plugin-0.1.0.dist-info/RECORD
