Metadata-Version: 2.4
Name: gauge-pybuild-plugin
Version: 0.1.0
Summary: Python build plugin for Gauge testing framework - Poetry, UV, and setuptools integration
Project-URL: Homepage, https://github.com/lirany1/gauge-pybuild-plugin
Project-URL: Repository, https://github.com/lirany1/gauge-pybuild-plugin
Project-URL: Documentation, https://github.com/lirany1/gauge-pybuild-plugin
Project-URL: Issues, https://github.com/lirany1/gauge-pybuild-plugin/issues
Author-email: Your Name <your.email@example.com>
License: Apache-2.0
License-File: LICENSE
Keywords: automation,gauge,plugin,poetry,setuptools,testing,uv
Classifier: Development Status :: 4 - Beta
Classifier: Intended Audience :: Developers
Classifier: License :: OSI Approved :: Apache Software License
Classifier: Operating System :: OS Independent
Classifier: Programming Language :: Python :: 3
Classifier: Programming Language :: Python :: 3.8
Classifier: Programming Language :: Python :: 3.9
Classifier: Programming Language :: Python :: 3.10
Classifier: Programming Language :: Python :: 3.11
Classifier: Programming Language :: Python :: 3.12
Classifier: Programming Language :: Python :: 3.13
Classifier: Topic :: Software Development :: Libraries :: Python Modules
Classifier: Topic :: Software Development :: Testing
Requires-Python: >=3.8
Requires-Dist: click>=8.0.0
Requires-Dist: pydantic>=2.0.0
Requires-Dist: toml>=0.10.2
Provides-Extra: dev
Requires-Dist: black>=23.0.0; extra == 'dev'
Requires-Dist: isort>=5.12.0; extra == 'dev'
Requires-Dist: mypy>=1.0.0; extra == 'dev'
Requires-Dist: pre-commit>=3.0.0; extra == 'dev'
Requires-Dist: pytest-cov>=4.0.0; extra == 'dev'
Requires-Dist: pytest>=7.0.0; extra == 'dev'
Requires-Dist: ruff>=0.1.0; extra == 'dev'
Provides-Extra: poetry
Requires-Dist: poetry>=1.4.0; extra == 'poetry'
